sps_c/DES.py
sps_c/S_DES.py
sps_c/__init__.py
sps_c/aes.py
sps_c/aes_mc.py
sps_c/ciphers.py
sps_c/dh_mitm.py
sps_c/ds.py
sps_c/elgamal.py
sps_c/hm.py
sps_c/rsa.py
sps_c/socketing.py
sps_crypto-1.0.79.dist-info/LICENSE
sps_crypto-1.0.79.dist-info/METADATA
sps_crypto-1.0.79.dist-info/WHEEL
sps_crypto-1.0.79.dist-info/entry_points.txt
sps_crypto-1.0.79.dist-info/top_level.txt
sps_crypto-1.0.79.dist-info/RECORD
