Metadata-Version: 2.1
Name: sps_crypto
Version: 1.0.79
Summary: Pure-Python implementation of cryptographic algorithms (RSA, ElGamal, AES, DES, Diffie-Hellman)
Home-page: https://github.com/amspsingh04/sps_crypto
Author: Shourya Pratap Singh
Author-email: sp.singh@gmail.com
Project-URL: Bug Reports, https://github.com/amspsingh04/sps_crypto/issues
Project-URL: Source, https://github.com/amspsingh04/sps_crypto
Project-URL: Documentation, https://github.com/amspsingh04/sps_crypto/blob/main/README.md
Keywords: cryptography,educational,rsa,elgamal,aes,des,diffie-hellman,digital signatures
Classifier: Development Status :: 4 - Beta
Classifier: Intended Audience :: Education
Classifier: Intended Audience :: Developers
Classifier: Intended Audience :: Science/Research
Classifier: Topic :: Security :: Cryptography
Classifier: License :: OSI Approved :: MIT License
Classifier: Programming Language :: Python :: 3 :: Only
Classifier: Programming Language :: Python :: 3.7
Classifier: Programming Language :: Python :: 3.8
Classifier: Programming Language :: Python :: 3.9
Classifier: Programming Language :: Python :: 3.10
Classifier: Operating System :: OS Independent
Classifier: Typing :: Typed
Requires-Python: >=3.7
License-File: LICENSE
Requires-Dist: cryptography>=3.4
Provides-Extra: dev
Requires-Dist: pytest>=6.0; extra == "dev"
Requires-Dist: pytest-cov>=2.0; extra == "dev"
Requires-Dist: mypy>=0.910; extra == "dev"
Requires-Dist: flake8>=3.9; extra == "dev"
Provides-Extra: docs
Requires-Dist: sphinx>=4.0; extra == "docs"
Requires-Dist: sphinx-rtd-theme>=0.5; extra == "docs"
